nutcracker/__init__.py
nutcracker/chiper/__init__.py
nutcracker/chiper/xor.py
nutcracker/codex/__init__.py
nutcracker/codex/base.py
nutcracker/codex/bomp.py
nutcracker/codex/bpp_codec.py
nutcracker/codex/bpp_cost.py
nutcracker/codex/codex.py
nutcracker/codex/codex1.py
nutcracker/codex/codex37_np.py
nutcracker/codex/codex47_np.py
nutcracker/codex/nutfont.py
nutcracker/codex/rle.py
nutcracker/codex/smap.py
nutcracker/decode_san_audio.py
nutcracker/earwax/__init__.py
nutcracker/earwax/preset.py
nutcracker/earwax/resource.py
nutcracker/graphics/__init__.py
nutcracker/graphics/frame.py
nutcracker/graphics/grid.py
nutcracker/graphics/image.py
nutcracker/kernel/__init__.py
nutcracker/kernel/align.py
nutcracker/kernel/buffer.py
nutcracker/kernel/chunk.py
nutcracker/kernel/element.py
nutcracker/kernel/index.py
nutcracker/kernel/iterchunk.py
nutcracker/kernel/preset.py
nutcracker/kernel/resource.py
nutcracker/kernel/runner.py
nutcracker/kernel/settings.py
nutcracker/kernel/structured.py
nutcracker/kernel/tree.py
nutcracker/py.typed
nutcracker/runner.py
nutcracker/smush/__init__.py
nutcracker/smush/ahdr.py
nutcracker/smush/anim.py
nutcracker/smush/compress.py
nutcracker/smush/decode.py
nutcracker/smush/element.py
nutcracker/smush/encode.py
nutcracker/smush/encode_san_seq.py
nutcracker/smush/fobj.py
nutcracker/smush/preset.py
nutcracker/smush/runner.py
nutcracker/smush/saud.py
nutcracker/smush/schema.py
nutcracker/smush/types.py
nutcracker/sputm/build.py
nutcracker/sputm/char/decode.py
nutcracker/sputm/char/encode.py
nutcracker/sputm/costume/__init__.py
nutcracker/sputm/costume/akos.py
nutcracker/sputm/costume/cost.py
nutcracker/sputm/index.py
nutcracker/sputm/preset.py
nutcracker/sputm/resource.py
nutcracker/sputm/room/encode_image.py
nutcracker/sputm/room/orgroom.py
nutcracker/sputm/room/pproom.py
nutcracker/sputm/room/proom.py
nutcracker/sputm/room/runner.py
nutcracker/sputm/runner.py
nutcracker/sputm/schema.py
nutcracker/sputm/script/__init__.py
nutcracker-0.3.14159.dist-info/entry_points.txt
nutcracker-0.3.14159.dist-info/LICENSE
nutcracker-0.3.14159.dist-info/WHEEL
nutcracker-0.3.14159.dist-info/METADATA
nutcracker-0.3.14159.dist-info/RECORD
