Metadata-Version: 2.1
Name: nutcracker
Version: 0.3.14159
Summary: Tools for editing resources in SCUMM games.
License: GPL-3.0-or-later
Keywords: scumm,sputm,smush,lucasarts,humongous
Author: BLooperZ
Author-email: blooperz@users.noreply.github.com
Requires-Python: >=3.9,<4.0
Classifier: Development Status :: 4 - Beta
Classifier: Environment :: Console
Classifier: Intended Audience :: Developers
Classifier: License :: OSI Approved :: GNU General Public License v3 (GPLv3)
Classifier: License :: OSI Approved :: GNU General Public License v3 or later (GPLv3+)
Classifier: Operating System :: OS Independent
Classifier: Programming Language :: Python :: 3
Classifier: Programming Language :: Python :: 3.9
Classifier: Topic :: Games/Entertainment
Classifier: Topic :: Software Development :: Build Tools
Classifier: Topic :: Utilities
Requires-Dist: Pillow (>=8.0.1,<9.0.0)
Requires-Dist: PyYAML (>=5.4.1,<6.0.0)
Requires-Dist: deal (>=4.5.0,<5.0.0)
Requires-Dist: numpy (>=1.19.1,<2.0.0)
Requires-Dist: parse (>=1.18.0,<2.0.0)
Requires-Dist: typer (>=0.3.2,<0.4.0)
Project-URL: repository, https://github.com/blooperz/nutcracker
